{
    "os": "Linux-3.10.0-1160.el7.x86_64-x86_64-with-centos-7.9.2009-Core",
    "python": "3.7.13",
    "heartbeatAt": "2022-12-20T02:14:16.145754",
    "startedAt": "2022-12-20T02:14:13.167958",
    "docker": null,
    "cuda": null,
    "args": [
        "--config",
        "config.json"
    ],
    "state": "running",
    "program": "train.py",
    "codePath": "train.py",
    "git": {
        "remote": "git@github.com:vincent40416/SkillTrendPrediction.git",
        "commit": "d2d87a658cffac9623a8f000683a64862df90e49"
    },
    "email": "vincent40416@gmail.com",
    "root": "/home/wchao/SkillTrendPrediction",
    "host": "localhost.localdomain",
    "username": "wchao",
    "executable": "/home/wchao/anaconda3/envs/skillkg/bin/python",
    "cpu_count": 24,
    "cpu_count_logical": 48,
    "cpu_freq": {
        "current": 1.4393958333333332,
        "min": 1000.0,
        "max": 3200.0
    },
    "cpu_freq_per_core": [
        {
            "current": 1.051,
            "min": 1000.0,
            "max": 3200.0
        },
        {
            "current": 2.3,
            "min": 1000.0,
            "max": 3200.0
        },
        {
            "current": 2.3,
            "min": 1000.0,
            "max": 3200.0
        },
        {
            "current": 1.0,
            "min": 1000.0,
            "max": 3200.0
        },
        {
            "current": 0.999,
            "min": 1000.0,
            "max": 3200.0
        },
        {
            "current": 2.284,
            "min": 1000.0,
            "max": 3200.0
        },
        {
            "current": 1.295,
            "min": 1000.0,
            "max": 3200.0
        },
        {
            "current": 1.044,
            "min": 1000.0,
            "max": 3200.0
        },
        {
            "current": 1.071,
            "min": 1000.0,
            "max": 3200.0
        },
        {
            "current": 1.066,
            "min": 1000.0,
            "max": 3200.0
        },
        {
            "current": 2.168,
            "min": 1000.0,
            "max": 3200.0
        },
        {
            "current": 1.04,
            "min": 1000.0,
            "max": 3200.0
        },
        {
            "current": 1.058,
            "min": 1000.0,
            "max": 3200.0
        },
        {
            "current": 0.999,
            "min": 1000.0,
            "max": 3200.0
        },
        {
            "current": 1.284,
            "min": 1000.0,
            "max": 3200.0
        },
        {
            "current": 1.004,
            "min": 1000.0,
            "max": 3200.0
        },
        {
            "current": 1.079,
            "min": 1000.0,
            "max": 3200.0
        },
        {
            "current": 1.047,
            "min": 1000.0,
            "max": 3200.0
        },
        {
            "current": 2.226,
            "min": 1000.0,
            "max": 3200.0
        },
        {
            "current": 1.695,
            "min": 1000.0,
            "max": 3200.0
        },
        {
            "current": 2.36,
            "min": 1000.0,
            "max": 3200.0
        },
        {
            "current": 1.179,
            "min": 1000.0,
            "max": 3200.0
        },
        {
            "current": 1.099,
            "min": 1000.0,
            "max": 3200.0
        },
        {
            "current": 1.167,
            "min": 1000.0,
            "max": 3200.0
        },
        {
            "current": 1.027,
            "min": 1000.0,
            "max": 3200.0
        },
        {
            "current": 2.293,
            "min": 1000.0,
            "max": 3200.0
        },
        {
            "current": 1.889,
            "min": 1000.0,
            "max": 3200.0
        },
        {
            "current": 1.011,
            "min": 1000.0,
            "max": 3200.0
        },
        {
            "current": 0.999,
            "min": 1000.0,
            "max": 3200.0
        },
        {
            "current": 0.999,
            "min": 1000.0,
            "max": 3200.0
        },
        {
            "current": 1.079,
            "min": 1000.0,
            "max": 3200.0
        },
        {
            "current": 1.003,
            "min": 1000.0,
            "max": 3200.0
        },
        {
            "current": 1.099,
            "min": 1000.0,
            "max": 3200.0
        },
        {
            "current": 1.026,
            "min": 1000.0,
            "max": 3200.0
        },
        {
            "current": 2.244,
            "min": 1000.0,
            "max": 3200.0
        },
        {
            "current": 1.389,
            "min": 1000.0,
            "max": 3200.0
        },
        {
            "current": 1.082,
            "min": 1000.0,
            "max": 3200.0
        },
        {
            "current": 1.013,
            "min": 1000.0,
            "max": 3200.0
        },
        {
            "current": 2.347,
            "min": 1000.0,
            "max": 3200.0
        },
        {
            "current": 1.425,
            "min": 1000.0,
            "max": 3200.0
        },
        {
            "current": 2.199,
            "min": 1000.0,
            "max": 3200.0
        },
        {
            "current": 1.124,
            "min": 1000.0,
            "max": 3200.0
        },
        {
            "current": 2.521,
            "min": 1000.0,
            "max": 3200.0
        },
        {
            "current": 2.299,
            "min": 1000.0,
            "max": 3200.0
        },
        {
            "current": 2.286,
            "min": 1000.0,
            "max": 3200.0
        },
        {
            "current": 1.207,
            "min": 1000.0,
            "max": 3200.0
        },
        {
            "current": 1.072,
            "min": 1000.0,
            "max": 3200.0
        },
        {
            "current": 1.198,
            "min": 1000.0,
            "max": 3200.0
        }
    ],
    "disk": {
        "total": 49.9755859375,
        "used": 3.2728347778320312
    },
    "gpu": "NVIDIA GeForce RTX 3090",
    "gpu_count": 4,
    "gpu_devices": [
        {
            "name": "NVIDIA GeForce RTX 3090",
            "memory_total": 25769803776
        },
        {
            "name": "NVIDIA GeForce RTX 3090",
            "memory_total": 25769803776
        },
        {
            "name": "NVIDIA GeForce RTX 3090",
            "memory_total": 25769803776
        },
        {
            "name": "NVIDIA GeForce RTX 3090",
            "memory_total": 25769803776
        }
    ],
    "memory": {
        "total": 125.38863754272461
    }
}
